README.rst
setup.py
./src/__init__.py
./src/yubikey_totp_gui.py
yubikey_totp_gui.egg-info/PKG-INFO
yubikey_totp_gui.egg-info/SOURCES.txt
yubikey_totp_gui.egg-info/dependency_links.txt
yubikey_totp_gui.egg-info/entry_points.txt
yubikey_totp_gui.egg-info/requires.txt
yubikey_totp_gui.egg-info/top_level.txt