Metadata-Version: 1.1
Name: yubikey-totp-gui
Version: 0.3.1
Summary: UNKNOWN
Home-page: https://github.com/ldrumm/yubikey-totp-gui
Author: Luke Drummond
Author-email: luke@lukedrummond.net
License: 2 clause BSD
Platform: UNKNOWN
Classifier: Development Status :: 3 - Alpha
Classifier: Topic :: Utilities
Classifier: Topic :: Security
Classifier: Intended Audience :: End Users/Desktop
Classifier: Operating System :: POSIX
Classifier: License :: OSI Approved :: BSD License
